autowing/__init__.py
autowing/appium/actions.py
autowing/appium/fixture.py
autowing/core/__init__.py
autowing/core/ai_context.py
autowing/core/ai_fixture_base.py
autowing/core/cache/cache_manager.py
autowing/core/llm/__init__.py
autowing/core/llm/base.py
autowing/core/llm/client/__init__.py
autowing/core/llm/client/deepseek.py
autowing/core/llm/client/doubao.py
autowing/core/llm/client/openai.py
autowing/core/llm/client/qwen.py
autowing/core/llm/factory.py
autowing/playwright/fixture.py
autowing/selenium/fixture.py
autowing/utils/transition.py
autowing-0.6.2.dist-info/licenses/LICENSE
autowing-0.6.2.dist-info/METADATA
autowing-0.6.2.dist-info/WHEEL
autowing-0.6.2.dist-info/RECORD
