Metadata-Version: 2.4
Name: autowing
Version: 0.6.2
Summary: auto-wing is a tool that uses LLM to assist automated testing.
License-File: LICENSE
Author: defnngj
Author-email: defnngj@gmail.com
Requires-Python: >=3.9
Classifier: Programming Language :: Python :: 3
Classifier: Programming Language :: Python :: 3.9
Classifier: Programming Language :: Python :: 3.10
Classifier: Programming Language :: Python :: 3.11
Classifier: Programming Language :: Python :: 3.12
Classifier: Programming Language :: Python :: 3.13
Classifier: Programming Language :: Python :: 3.14
Requires-Dist: dashscope (>=1.25.9,<2.0.0)
Requires-Dist: loguru (>=0.7.3,<0.8.0)
Requires-Dist: openai (>=2.15.0,<3.0.0)
Requires-Dist: python-dotenv (>=1.2.1,<2.0.0)
Project-URL: Homepage, https://github.com/SeldomQA/auto-wing
Project-URL: Repository, https://github.com/SeldomQA/auto-wing
